sketchpy/__init__.py
sketchpy/canvas.py
sketchpy/library.py
sketchpy/test.py
sketchpy/pytransform/__init__.py
sketchpy-0.1.8.dist-info/LICENSE
sketchpy-0.1.8.dist-info/METADATA
sketchpy-0.1.8.dist-info/WHEEL
sketchpy-0.1.8.dist-info/top_level.txt
sketchpy-0.1.8.dist-info/RECORD
