Metadata-Version: 2.1
Name: sketchpy
Version: 0.1.8
Summary: sketchpy
Home-page: UNKNOWN
Author: Mr Mystery
Author-email: sriramanand23@gmail.com
License: UNKNOWN
Keywords: python,sketch,drawing,animation,code hub,pencil sketch,painting,sketchpy,draw,sketching
Platform: UNKNOWN
Classifier: Development Status :: 1 - Planning
Classifier: Intended Audience :: Developers
Classifier: Programming Language :: Python :: 3
Classifier: Operating System :: Unix
Classifier: Operating System :: MacOS :: MacOS X
Classifier: Operating System :: Microsoft :: Windows
Requires-Dist: opencv-python
Requires-Dist: turtle (==0.0.1)
Requires-Dist: wheel
Requires-Dist: Pillow
Requires-Dist: svg.path
Requires-Dist: svgpathtools
Requires-Dist: pyarmor
Requires-Dist: tqdm
Requires-Dist: requests
Requires-Dist: geocoder
Requires-Dist: geopy
